liftwing/__init__.py
liftwing/__main__.py
liftwing/models/__init__.py
liftwing/models/article_topic.py
liftwing/models/language_id.py
liftwing/models/liftwing_model.py
liftwing/models/readability.py
liftwing/models/revertrisk.py
liftwing/models/revertrisk_multilingual.py
liftwing/models/revscoring.py
liftwing-0.1.1.dist-info/METADATA
liftwing-0.1.1.dist-info/WHEEL
liftwing-0.1.1.dist-info/top_level.txt
liftwing-0.1.1.dist-info/RECORD
