Metadata-Version: 2.1
Name: liftwing
Version: 0.1.1
Summary: A python client to interact with Machine Learning microservices hosted on Lift Wing
Author-email: Mercelis Vaughan <mercelisvaughan@gmail.com>, WMF Machine Learning Team <ml@wikimedia.org>
Classifier: Programming Language :: Python :: 3
Requires-Python: >=3.9
Requires-Dist: requests
Requires-Dist: pydantic ~=2.7
